odoo/addons/website_sale_product_description/README.rst
odoo/addons/website_sale_product_description/__init__.py
odoo/addons/website_sale_product_description/__manifest__.py
odoo/addons/website_sale_product_description/data/demo_website_sale_product_description.xml
odoo/addons/website_sale_product_description/i18n/ca.po
odoo/addons/website_sale_product_description/i18n/es.po
odoo/addons/website_sale_product_description/i18n/es_ES.po
odoo/addons/website_sale_product_description/i18n/nl.po
odoo/addons/website_sale_product_description/i18n/website_sale_product_description.pot
odoo/addons/website_sale_product_description/models/__init__.py
odoo/addons/website_sale_product_description/models/product.py
odoo/addons/website_sale_product_description/readme/CONTRIBUTORS.rst
odoo/addons/website_sale_product_description/readme/DESCRIPTION.rst
odoo/addons/website_sale_product_description/readme/USAGE.rst
odoo/addons/website_sale_product_description/static/description/icon.png
odoo/addons/website_sale_product_description/static/description/index.html
odoo/addons/website_sale_product_description/static/description/product.png
odoo/addons/website_sale_product_description/static/description/website-product.png
odoo/addons/website_sale_product_description/views/product_template.xml
odoo/addons/website_sale_product_description/views/website_sale_template.xml
odoo13_addon_website_sale_product_description-13.0.1.0.1.dev6.dist-info/METADATA
odoo13_addon_website_sale_product_description-13.0.1.0.1.dev6.dist-info/WHEEL
odoo13_addon_website_sale_product_description-13.0.1.0.1.dev6.dist-info/top_level.txt
odoo13_addon_website_sale_product_description-13.0.1.0.1.dev6.dist-info/RECORD
